cv2_detection/__init__.py
cv2_detection/cv2_image_threshing.py
cv2_detection/cv2_objects.py
cv2_detection/cv2_painting.py
cv2_detection/object_detection/__init__.py
cv2_detection/object_detection/indication.py
cv2_detection/object_detection/painting.py
cv2_detection/object_detection/detection/__init__.py
cv2_detection/object_detection/detection/contour_processing.py
cv2_detection/object_detection/detection/image_threshing.py
cv2_detection/object_detection/detection/object_detection.py
cv2_detection/object_detection/detection/objects.py
cv2_detection-1.2.dist-info/LICENSE
cv2_detection-1.2.dist-info/WHEEL
cv2_detection-1.2.dist-info/METADATA
cv2_detection-1.2.dist-info/RECORD
