Metadata-Version: 2.1
Name: cv2_detection
Version: 1.2
Summary: Object detection using opencv
Keywords: opencv,cv2,object,detection
Author-email: sfkan6 <sfkan6@yandex.ru>
Requires-Python: >=3.7
Classifier: Programming Language :: Python :: 3
Classifier: License :: OSI Approved :: Apache Software License
Requires-Dist: opencv-python-headless>=4.10.0.84
Project-URL: Home, https://github.com/sfkan6/opencv-object-detection
